snipar/__init__.py
snipar/config.py
snipar/correlate.py
snipar/docgen.py
snipar/errors.py
snipar/gtarray.py
snipar/gwas.py
snipar/ibd.py
snipar/ld.py
snipar/map.py
snipar/numrange.py
snipar/pedigree.py
snipar/pgs.py
snipar/pgs_am.py
snipar/preprocess.py
snipar/simulate.py
snipar/slmm.py
snipar/types.py
snipar/utilities.py
snipar/example/__init__.py
snipar/example/simulate_phenotype.py
snipar/example/snipar_example_data.py
snipar/example/example_data/agesex.txt
snipar/example/example_data/chr_1.bed
snipar/example/example_data/chr_1.bgen
snipar/example/example_data/chr_1.bim
snipar/example/example_data/chr_1.fam
snipar/example/example_data/chr_1.sample
snipar/example/example_data/chr_1.sibs
snipar/example/example_data/chr_1.trios
snipar/example/example_data/chr_1.trios_sibs
snipar/example/example_data/chr_1.trios_sibs_singletons
snipar/example/example_data/chr_1.trios_singletons
snipar/example/example_data/chr_1_sibs.bgen
snipar/example/example_data/chr_1_trios.bgen
snipar/example/example_data/chr_1_trios_sibs.bgen
snipar/example/example_data/chr_1_trios_sibs_singletons.bgen
snipar/example/example_data/chr_1_trios_singletons.bgen
snipar/example/example_data/direct_weights.txt
snipar/example/example_data/estimate_sim_effects.py
snipar/example/example_data/genetic_map.txt
snipar/example/example_data/king.kin0
snipar/example/example_data/king.segments.gz
snipar/example/example_data/kingallsegs.txt
snipar/example/example_data/pedigree.txt
snipar/example/example_data/phenotype.effects.txt
snipar/example/example_data/phenotype.txt
snipar/imputation/__init__.py
snipar/imputation/impute_from_sibs.cpython-38-x86_64-linux-gnu.so
snipar/imputation/impute_from_sibs.pxd
snipar/imputation/impute_from_sibs.pyx
snipar/imputation/preprocess_data.py
snipar/read/__init__.py
snipar/read/bed.py
snipar/read/bgen.py
snipar/read/phenotype.py
snipar/scripts/__init__.py
snipar/scripts/correlate.py
snipar/scripts/gts_matrix.py
snipar-0.0.22.dist-info/LICENSE
snipar-0.0.22.dist-info/METADATA
snipar-0.0.22.dist-info/WHEEL
snipar-0.0.22.dist-info/top_level.txt
snipar-0.0.22.dist-info/RECORD
