Metadata-Version: 2.1
Name: snipar
Version: 0.0.22
Summary: Library and command line scripts for inferring identity-by-descent (IBD) segments shared between siblings, imputing missing parental genotypes, performing family based genome-wide association and polygenic score analyses.
Home-page: http://github.com/alexTISYoung/snipar
Download-URL: https://pypi.org/project/snipar/files
Author: Alexander Strudwick Young, Moeen Nehzati, Junming Guan
Author-email: alextisyoung@gmail.com
License: MIT
Keywords: statistics genetics
Classifier: Development Status :: 4 - Beta
Classifier: Intended Audience :: Science/Research
Classifier: Topic :: Scientific/Engineering :: Bio-Informatics
Classifier: License :: OSI Approved :: MIT License
Requires-Python: >=3.7
License-File: LICENSE
Requires-Dist: numpy ==1.21.1
Requires-Dist: scipy ==1.7.1
Requires-Dist: bgen-reader ==4.0.7
Requires-Dist: pandas ==1.1.4
Requires-Dist: pysnptools ==0.5.3
Requires-Dist: networkx ==2.5
Requires-Dist: h5py ==3.6.0
Requires-Dist: pooch ==1.5.1
Requires-Dist: numba ==0.55.0
Requires-Dist: gitpython ==3.1.24
Requires-Dist: scikit-learn ==1.0.2
Requires-Dist: statsmodels ==0.13.2
Requires-Dist: numdifftools >=0.9.39
